default_gui/__init__.py
default_gui/gui.py
bell_gui-0.0.1.dist-info/LICENSE
bell_gui-0.0.1.dist-info/METADATA
bell_gui-0.0.1.dist-info/WHEEL
bell_gui-0.0.1.dist-info/top_level.txt
bell_gui-0.0.1.dist-info/RECORD
