Metadata-Version: 2.1
Name: bell-gui
Version: 0.0.1
Summary: Simple gui collection
Home-page: https://github.com/FabianBell/Packages
Author: Fabian Bell
Author-email: fabianx.bell@gmail.com
License: MIT
Platform: UNKNOWN
Classifier: Programming Language :: Python :: 3
Classifier: License :: OSI Approved :: MIT License
